autoserve/__init__.py
autoserve/__main__.py
autoserve/seldon/__init__.py
autoserve/seldon/sklearn.py
autoserve-1.0.dist-info/LICENSE
autoserve-1.0.dist-info/METADATA
autoserve-1.0.dist-info/WHEEL
autoserve-1.0.dist-info/entry_points.txt
autoserve-1.0.dist-info/top_level.txt
autoserve-1.0.dist-info/RECORD
