Metadata-Version: 2.1
Name: autoserve
Version: 1.0
Summary: Model Serving Automation
Home-page: UNKNOWN
Author: subhrajit
Author-email: techbiglover@gmail.com
License: MIT
Platform: UNKNOWN
Requires-Python: >=3.7, <4
Requires-Dist: typer (>=0.3.0)
Requires-Dist: kubernetes (==17.17.0)
